[
 {
  "Title": "AIMS Neuroscience",
  "URL": "http://www.aimspress.com/news/160.html",
  "Notes": [
   {
    "Link": "http://orca.cf.ac.uk/59475/1/AN2.pdf",
    "Description": "Editorial"
   },
   {
    "Link": "http://orca.cf.ac.uk/59475/1/AN2.pdf",
    "Description": "Guidelines"
   }
  ]
 },
 {
  "Title": "Attention, Perception, and Psychophysics",
  "URL": "http://www.springer.com/psychology/cognitive+psychology/journal/13414",
  "Notes": [
   {
    "Link": "http://link.springer.com/content/pdf/10.3758%2Fs13414-013-0502-5.pdf",
    "Description": "Editorial"
   }
  ]
 },
 {
  "Title": "Cognition and Emotion",
  "URL": "http://www.tandfonline.com/toc/pcem20/current",
  "Notes": [
   {
    "Link": "http://www.tandfonline.com/doi/full/10.1080/02699931.2015.1026223",
    "Description": "Editorial"
   },
   {
    "Link": "http://explore.tandfonline.com/page/beh/pcem-registered-reports-of-replication-studies/",
    "Description": "Guidelines"
   }
  ]
 },
 {
  "Title": "Cognitive Research: Principles and Implications",
  "URL": "http://cognitiveresearchjournal.springeropen.com/",
  "Notes": [
   {
    "Link": "http://link.springer.com/article/10.3758/s13414-013-0502-5/fulltext.html",
    "Description": "Editorial"
   },
   {
    "Link": "http://cognitiveresearchjournal.springeropen.com/submission-guidelines/preparing-your-manuscript/registered-reports-and-replications",
    "Description": "Guidelines"
   }
  ]
 },
 {
  "Title": "Comprehensive Results in Social Psychology",
  "URL": "http://www.tandfonline.com/loi/rrsp20",
  "Notes": [
   {
    "Link": "http://www.tandfonline.com/doi/full/10.1080/23743603.2015.1070611",
    "Description": "Editorial"
   },
   {
    "Link": "http://www.tandf.co.uk/journals/authors/rrsp-submission-guidelines.pdf",
    "Description": "Guidelines"
   }
  ]
 },
 {
  "Title": "Cortex",
  "URL": "http://www.journals.elsevier.com/cortex",
  "Notes": [
   {
    "Link": "https://dl.dropboxusercontent.com/u/15691907/Chambers_2013b_Cortex.pdf",
    "Description": "Editorial"
   },
   {
    "Link": "http://cdn.elsevier.com/promis_misc/PROMIS%20pub_idt_CORTEX%20Guidelines_RR_29_04_2013.pdf",
    "Description": "Guidelines"
   }
  ]
 },
 {
  "Title": "Drug and Alcohol Dependence",
  "URL": "http://www.journals.elsevier.com/drug-and-alcohol-dependence",
  "Notes": [
   {
    "Link": "https://dl.dropboxusercontent.com/u/15691907/DAD_RegisteredReports_Editorial.pdf",
    "Description": "Editorial"
   },
   {
    "Link": "http://cdn.elsevier.com/promis_misc/DAD_RR_GL_final.pdf",
    "Description": "Guidelines"
   }
  ]
 },
 {
  "Title": "European Journal of Neuroscience",
  "URL": "http://onlinelibrary.wiley.com/journal/10.1111/(ISSN)1460-9568",
  "Notes": [
   {
    "Link": "http://onlinelibrary.wiley.com/journal/10.1111/(ISSN)1460-9568/homepage/ForAuthors.html#Index_2_Types_of_Manuscripts",
    "Description": "Instructions"
   },
   {
    "Link": "http://onlinelibrary.wiley.com/store/10.1111/(ISSN)1460-9568/asset/homepages/Registered_Report_author_guide.pdf?v=1&s=5cddc7d3d6ff7938552942c6bf4b35fab38edec3&isAguDoi=false",
    "Description": "Guidelines"
   }
  ]
 },
 {
  "Title": "Experimental Psychology",
  "URL": "https://us.hogrefe.com/products/journals/exppsy",
  "Notes": [
   {
    "Link": "https://us.hogrefe.com/fileadmin/user_upload/global/journals/Hogrefe_Publishing/Experimental_Psychology/Zea_INstructions_extended_final.pdf",
    "Description": "Guidelines"
   }
  ]
 },
 {
  "Title": "Human Movement Science",
  "URL": "http://www.journals.elsevier.com/human-movement-science/",
  "Notes": [
   {
    "Link": "https://dl.dropboxusercontent.com/u/15691907/1-s2.0-S0167945715001414-main.pdf",
    "Description": "Editorial"
   },
   {
    "Link": "http://cdn.elsevier.com/promis_misc/Guidelines_Registered_Reports_HMS.pdf",
    "Description": "Guidelines"
   }
  ]
 },
 {
  "Title": "International Journal of Psychophysiology",
  "URL": "http://www.journals.elsevier.com/international-journal-of-psychophysiology",
  "Notes": [
   {
    "Link": "http://www.sciencedirect.com/science/article/pii/S0167876016300381",
    "Description": "Editorial"
   },
   {
    "Link": "http://cdn.elsevier.com/promis_misc/Guidelines_Registered_Reports_HMS.pdf",
    "Description": "Guidelines"
   }
  ]
 },
 {
  "Title": "Journal of Accounting Research",
  "URL": "http://onlinelibrary.wiley.com/journal/10.1111/(ISSN)1475-679X",
  "Notes": [
   {
    "Link": "https://research.chicagobooth.edu/arc/journal-of-accounting-research/call-for-papers#simple2",
    "Description": "Request for Papers"
   },
   {
    "Link": "https://research.chicagobooth.edu/~/media/9130C8D2A8D54E1598D704C8D9BF922E.pdf",
    "Description": "Guidelines"
   }
  ]
 },
 {
  "Title": "Journal of Business and Psychology",
  "URL": "http://link.springer.com/journal/10869",
  "Notes": [
   {
    "Link": "https://osf.io/ep2hs/",
    "Description": "Editorial"
   }
  ]
 },
 {
  "Title": "Journal of Cognitive Enhancement",
  "URL": "http://www.springer.com/psychology/cognitive+psychology/journal/41465",
  "Notes": [
   {
    "Link": "",
    "Description": ""
   }
  ]
 },
 {
  "Title": "Journal of European Psychology Students ",
  "URL": "http://jeps.efpsa.org/",
  "Notes": [
   {
    "Link": "http://jeps.efpsa.org/articles/10.5334/jeps.401/",
    "Description": "Editorial"
   },
   {
    "Link": "http://jeps.efpsa.org/about/submissions/#Registered%20Reports",
    "Description": "Guidelines"
   }
  ]
 },
 {
  "Title": "Journal of Experimental Political Science",
  "URL": "https://www.cambridge.org/core/journals/journal-of-experimental-political-science",
  "Notes": [
   {
    "Link": "https://www.cambridge.org/core/journals/journal-of-experimental-political-science/article/continuity-and-change-at-the-journal-of-experimental-political-science/6006305AB40826371D36DE286A518693/core-reader",
    "Description": "Editorial"
   },
   {
    "Link": "",
    "Description": " Details to Follow"
   }
  ]
 },
 {
  "Title": "Journal of Media Psychology",
  "URL": "https://us.hogrefe.com/products/journals/jmp",
  "Notes": [
   {
    "Link": "https://dl.dropboxusercontent.com/u/15691907/JMP_2015_editorial.pdf",
    "Description": "Editorial"
   },
   {
    "Link": "https://us.hogrefe.com/fileadmin/user_upload/global/journals/Hogrefe_Publishing/Journal_of_Media_Psychology/zmp_author_instructions_general_2016-05-06.pdf",
    "Description": "Guidelines"
   }
  ]
 },
 {
  "Title": "Journal of Personnel Psychology",
  "URL": "https://us.hogrefe.com/products/journals/jpp",
  "Notes": [
   {
    "Link": "http://econtent.hogrefe.com/doi/abs/10.1027/1866-5888/a000140",
    "Description": "Editorial"
   },
   {
    "Link": "https://us.hogrefe.com/fileadmin/user_upload/global/journals/Hogrefe_Publishing/Journal_of_Personnel_Psychology/pps_author_instructions_RegisteredReports_2016-01.pdf",
    "Description": "Guidelines"
   }
  ]
 },
 {
  "Title": "NFS Journal",
  "URL": "http://www.journals.elsevier.com/nfs-journal/",
  "Notes": [
   {
    "Link": "http://www.journals.elsevier.com/nfs-journal/news/introducing-new-nfs-journal/",
    "Description": "Announcement"
   },
   {
    "Link": "http://cdn.elsevier.com/promis_misc/NFS_Reviewer_Guidelines.pdf",
    "Description": "Guidelines"
   }
  ]
 },
 {
  "Title": "Nature Human Behaviour",
  "URL": "http://www.nature.com/nathumbehav/",
  "Notes": [
   {
    "Link": "https://twitter.com/chrisdc77/status/743814766225928192",
    "Description": "Announcement"
   },
   {
    "Link": "",
    "Description": " Details to Follow"
   }
  ]
 },
 {
  "Title": "Nicotine & Tobacco Research",
  "URL": "http://ntr.oxfordjournals.org/",
  "Notes": [
   {
    "Link": "https://m.ntr.oxfordjournals.org/content/early/2016/02/11/ntr.ntw031.full.pdf",
    "Description": "Guidelines"
   }
  ]
 },
 {
  "Title": "Perspectives on Psychological Science",
  "URL": "http://pps.sagepub.com/",
  "Notes": [
   {
    "Link": "http://www.psychologicalscience.org/index.php/replication",
    "Description": "Guidelines"
   }
  ]
 },
 {
  "Title": "Royal Society Open Science",
  "URL": "http://rsos.royalsocietypublishing.org/",
  "Notes": [
   {
    "Link": "https://blogs.royalsociety.org/publishing/registered-reports/",
    "Description": "Blog"
   },
   {
    "Link": "http://rsos.royalsocietypublishing.org/content/registered-reports",
    "Description": "Guidelines"
   }
  ]
 },
 {
  "Title": "Stress and Health",
  "URL": "http://onlinelibrary.wiley.com/journal/10.1002/(ISSN)1532-2998",
  "Notes": [
   {
    "Link": "http://onlinelibrary.wiley.com/doi/10.1002/smi.2645/full",
    "Description": "Editorial"
   },
   {
    "Link": "http://onlinelibrary.wiley.com/store/10.1002/%28ISSN%291532-2998/asset/homepages/Author_Submission_Guidelines_for_Registered_Reports.pdf?v=1&s=e7fa5a44425ff03c92bc5fc28714fb580ee86e7a",
    "Description": "Guidelines"
   }
  ]
 },
 {
  "Title": "The Leadership Quarterly",
  "URL": "http://www.journals.elsevier.com/the-leadership-quarterly",
  "Notes": [
   {
    "Link": "http://www.journals.elsevier.com/the-leadership-quarterly/news/john-antonakis-looks-forward-to-taking-the-reins-in-2017",
    "Description": "Announcement"
   },
   {
    "Link": "",
    "Description": " Details to Follow"
   }
  ]
 },
 {
  "Title": "Work, Aging and Retirement",
  "URL": "http://workar.oxfordjournals.org/",
  "Notes": [
   {
    "Link": "http://workar.oxfordjournals.org/about",
    "Description": "Guidelines"
   }
  ]
 }
]